{"scientific_name": "Galium spurium", "family": {"en": "Rubiaceae", "fr": "Rubiaceae"}, "common_name": {"en": "False cleavers", "fr": "Gaillet bâtard"}, "duration_of_life_cycle": {"en": ["Annual"], "fr": ["Annuelle"]}, "seed_or_fruit_type": {"en": "Schizocarp", "fr": "Schizocarpe"}, "identification_features": {"seed_length": [1.0, 2.5], "seed_width": [], "shape": {"en": "Fruit globose to oval with a highly visible hole on the ventral side", "fr": "Fruit de forme globuleuse à elliptique, présentant un trou bien visible sur la face ventrale"}, "surface_texture": {"en": "The surface is covered in hooked bristles with non-tuberculate bases, fruits occasionally smooth", "fr": "La surface est recouverte de soies crochues avec une base non tuberculée; fruits parfois lisses"}, "colour": {"en": "Fruit grey-brown with white bristles", "fr": "Fruit brun-gris avec des soies blanches"}, "other_features": {"en": "The hole on the ventral side of the fruit is typically a transverse oval", "fr": "Le trou sur la face ventrale du fruit est généralement de forme elliptique transverse"}}, "images": {"photos": ["https://inspection.canada.ca/False_cleavers_fruits.jpg", "https://inspection.canada.ca/False_cleavers_fruit.jpg", "https://inspection.canada.ca/False_cleavers_fruit_close-up_of_surface.jpg", "https://inspection.canada.ca/False_cleavers_fruit.jpg", "https://inspection.canada.ca/False_cleavers_fruit.jpg", "https://inspection.canada.ca/False_cleavers_fruit_cross-section.jpg"], "similar_species": ["https://inspection.canada.ca/Cleavers_fruits.jpg", "https://inspection.canada.ca/Cleavers_fruit.jpg", "https://inspection.canada.ca/Cleavers_fruit_close-up_of_surface.jpg"]}}